django_spoll/__init__.py
django_spoll/admin.py
django_spoll/apps.py
django_spoll/helpers.py
django_spoll/models.py
django_spoll/tests.py
django_spoll/urls.py
django_spoll/views.py
django_spoll/migrations/0001_initial.py
django_spoll/migrations/__init__.py
django_spoll/static/soccerpoll/styles.css
django_spoll/static/soccerpoll/images/background.jpg
django_spoll/templates/soccerpoll/detail.html
django_spoll/templates/soccerpoll/index.html
django_spoll/templates/soccerpoll/results.html
django_spoll-0.4.0.dist-info/licenses/LICENSE
django_spoll-0.4.0.dist-info/METADATA
django_spoll-0.4.0.dist-info/WHEEL
django_spoll-0.4.0.dist-info/top_level.txt
django_spoll-0.4.0.dist-info/RECORD
