Metadata-Version: 2.4
Name: django-spoll
Version: 0.4.0
Summary: A Django app to conduct web-based soccer polls.
Author-email: Omar Abraham <oym7@msn.com>
License-Expression: BSD-3-Clause
Project-URL: Homepage, http://127.0.0.1:8000/soccerpoll/
Classifier: Environment :: Web Environment
Classifier: Framework :: Django
Classifier: Framework :: Django :: 6.0
Classifier: Intended Audience :: Developers
Classifier: Operating System :: OS Independent
Classifier: Programming Language :: Python
Classifier: Programming Language :: Python :: 3
Classifier: Programming Language :: Python :: 3 :: Only
Classifier: Programming Language :: Python :: 3.10
Classifier: Programming Language :: Python :: 3.11
Classifier: Programming Language :: Python :: 3.12
Classifier: Programming Language :: Python :: 3.13
Classifier: Programming Language :: Python :: 3.14
Classifier: Topic :: Internet :: WWW/HTTP
Classifier: Topic :: Internet :: WWW/HTTP :: Dynamic Content
Requires-Python: >=3.14.1
License-File: LICENSE
Requires-Dist: django>=6.0
Dynamic: license-file
